tess/__init__.py
tess/_version.py
tess/ida/__init__.py
tess/ida/_version.py
tess/ida/constants.py
tess/ida/download.py
tess/ida/pipeline.py
tess/ida/timeseries.py
tess/ida/dbase/__init__.py
tess/ida/dbase/api.py
tess/ida/dbase/schema.py
tess/ida/dbase/sql/__init__.py
tess/ida/dbase/sql/schema.sql
tess/ida/utils/__init__.py
tess/ida/utils/parser.py
tess/ida/utils/utils.py
tess_ida_tools-1.1.5.dist-info/licenses/LICENSE
tess_ida_tools-1.1.5.dist-info/METADATA
tess_ida_tools-1.1.5.dist-info/WHEEL
tess_ida_tools-1.1.5.dist-info/entry_points.txt
tess_ida_tools-1.1.5.dist-info/top_level.txt
tess_ida_tools-1.1.5.dist-info/RECORD
