Metadata-Version: 2.4
Name: tess-ida-tools
Version: 1.1.5
Summary: Collection of utilities to download and analize TESS Photometer Network data from IDA files
Author-email: Rafael González <rafael08@ucm.es>, Jaime Zamorano <jzamorano@fis.ucm.es>
License: MIT License
Project-URL: Homepage, https://github.com/STARS4ALL/TESS-IDA-TOOLS
Project-URL: Repository, https://github.com/STARS4ALL/TESS-IDA-TOOLS.git
Classifier: Programming Language :: Python :: 3.9
Classifier: Programming Language :: Python :: 3.10
Classifier: Programming Language :: Python :: 3.11
Classifier: Programming Language :: Python :: 3.12
Classifier: Development Status :: 4 - Beta
Classifier: Environment :: Console
Classifier: Intended Audience :: Science/Research
Classifier: License :: OSI Approved :: MIT License
Classifier: Operating System :: POSIX :: Linux
Classifier: Topic :: Scientific/Engineering :: Astronomy
Classifier: Topic :: Scientific/Engineering :: Atmospheric Science
Requires-Python: >=3.9
License-File: LICENSE
Requires-Dist: typing-extensions
Requires-Dist: StrEnum
Requires-Dist: python-decouple
Requires-Dist: python-dateutil
Requires-Dist: tabulate
Requires-Dist: aiofiles
Requires-Dist: aiohttp
Requires-Dist: aiodns
Requires-Dist: astropy
Requires-Dist: astroplan
Requires-Dist: lica>=1.0.1
Dynamic: license-file
